airflow_notify_sns/__init__.py
airflow_notify_sns/notify.py
airflow_notify_sns-0.0.2.dist-info/LICENSE
airflow_notify_sns-0.0.2.dist-info/METADATA
airflow_notify_sns-0.0.2.dist-info/WHEEL
airflow_notify_sns-0.0.2.dist-info/top_level.txt
airflow_notify_sns-0.0.2.dist-info/RECORD
