Metadata-Version: 2.1
Name: airflow-notify-sns
Version: 0.0.2
Summary: Publish Airflow notification errors to SNS Topic
Home-page: https://github.com/msantino/airflow-notify-sns
Author: Marcelo Santino
Author-email: marcelo@santino.dev
License: UNKNOWN
Platform: UNKNOWN
Classifier: Programming Language :: Python :: 3
Classifier: License :: OSI Approved :: MIT License
Classifier: Operating System :: OS Independent
